Academy2AI.py
academy2AI-1.0.5.dist-info/METADATA
academy2AI-1.0.5.dist-info/WHEEL
academy2AI-1.0.5.dist-info/top_level.txt
academy2AI-1.0.5.dist-info/RECORD
