Metadata-Version: 2.1
Name: academy2AI
Version: 1.0.5
Summary: Academy 4 Summer Course
